cfn_inline_lambda_linter/__init__.py
cfn_inline_lambda_linter/linter.py
cfn_inline_lambda_linter/main.py
cfn_inline_lambda_linter-0.1.7.dist-info/LICENSE.md
cfn_inline_lambda_linter-0.1.7.dist-info/METADATA
cfn_inline_lambda_linter-0.1.7.dist-info/WHEEL
cfn_inline_lambda_linter-0.1.7.dist-info/entry_points.txt
cfn_inline_lambda_linter-0.1.7.dist-info/RECORD
