Metadata-Version: 2.1
Name: cfn-inline-lambda-linter
Version: 0.1.7
Summary: Prints out linting errors found in inline cloudformation lambda code
License: MIT
Author: Saad Mohsin Khan
Author-email: saadk687@gmail.com
Requires-Python: >=3.9,<4.0
Classifier: License :: OSI Approved :: MIT License
Classifier: Programming Language :: Python :: 3
Classifier: Programming Language :: Python :: 3.9
Classifier: Programming Language :: Python :: 3.10
Classifier: Programming Language :: Python :: 3.11
Classifier: Programming Language :: Python :: 3.12
Requires-Dist: colorama (>=0.4.6,<0.5.0)
Requires-Dist: flake8 (>=7.1.1,<8.0.0)
Requires-Dist: pyyaml (>=6.0.2,<7.0.0)
Requires-Dist: typer (>=0.15.1,<0.16.0)
